{"type":"FeatureCollection","features":[{"type":"Feature","id":10,"geometry":{"type":"Point","coordinates":[-95.844306999999958,41.568985000000055]},"properties":{"OID":10,"Company":"Google","Data_Center_Location":"Council Bluffs, Iowa","Data_Generated_Per_Day__TB_":1025,"Data_Equivalent__DVDs_":1000000,"Latitude":41.568984999999998,"Longitude":-95.844307000000001,"Number_of_countries_served":"175+","Continents_served":"Africa, Americas, Asia, Europe, Oceania","DDLat":41.568984999999998,"DDLon":-95.844307000000001,"Location":"Council Bluffs, Iowa"}}]}