{"type":"FeatureCollection","features":[{"type":"Feature","id":2,"geometry":{"type":"Point","coordinates":[-80.650967999999978,35.389622000000031]},"properties":{"OID":2,"Company":"Apple","Data_Center_Location":"Maiden, North Carolina","Data_Generated_Per_Day__TB_":700,"Data_Equivalent__DVDs_":700000,"Latitude":35.389622000000003,"Longitude":-80.650968000000006,"Number_of_countries_served":"150+","Continents_served":"Africa, Americas, Asia, Europe, Oceania","DDLat":35.389622000000003,"DDLon":-80.650968000000006,"Location":"Maiden, North Carolina"}}]}