{"type":"FeatureCollection","features":[{"type":"Feature","id":6,"geometry":{"type":"Point","coordinates":[-112.07403699999998,33.44837700000005]},"properties":{"OID":6,"Company":"Digital Realty Trust","Data_Center_Location":"Phoenix, Arizona","Data_Generated_Per_Day__TB_":50,"Data_Equivalent__DVDs_":50000,"Latitude":33.448377000000001,"Longitude":-112.074037,"Number_of_countries_served":"150+","Continents_served":"Americas, Europe, Asia","DDLat":33.448377000000001,"DDLon":-112.074037,"Location":"Phoenix, Arizona"}}]}